piqueserver.libs/libstdc++-0530927c.so.6.0.32
piqueserver.libs/libgcc_s-1257a076.so.1
piqueserver-1.3.0.dist-info/LICENSE
piqueserver-1.3.0.dist-info/WHEEL
piqueserver-1.3.0.dist-info/RECORD
piqueserver-1.3.0.dist-info/top_level.txt
piqueserver-1.3.0.dist-info/entry_points.txt
piqueserver-1.3.0.dist-info/METADATA
piqueserver/statistics.py
piqueserver/_version.py
piqueserver/extensions.py
piqueserver/scheduler.py
piqueserver/__main__.py
piqueserver/version.py
piqueserver/map.py
piqueserver/ssh.py
piqueserver/banpublish.py
piqueserver/config.py
piqueserver/__init__.py
piqueserver/release.py
piqueserver/irc.py
piqueserver/networkdict.py
piqueserver/run.py
piqueserver/player.py
piqueserver/server.py
piqueserver/console.py
piqueserver/statusserver.py
piqueserver/auth.py
piqueserver/bansubscribe.py
piqueserver/commands.py
piqueserver/game_modes/tdm.py
piqueserver/game_modes/babel.py
piqueserver/game_modes/tow.py
piqueserver/game_modes/arena.py
piqueserver/game_modes/push.py
piqueserver/game_modes/freeforall.py
piqueserver/game_modes/__init__.py
piqueserver/game_modes/infiltration.py
piqueserver/game_modes/onectf.py
piqueserver/config/config.toml
piqueserver/config/README.md
piqueserver/config/game_modes/README.md
piqueserver/config/scripts/README.md
piqueserver/config/maps/classicgen.txt
piqueserver/config/maps/random.txt
piqueserver/utils/_async.py
piqueserver/utils/__init__.py
piqueserver/utils/_timeparse.py
piqueserver/scripts/trusted.py
piqueserver/scripts/votekick.py
piqueserver/scripts/aimbot2.py
piqueserver/scripts/afk.py
piqueserver/scripts/map_extensions.py
piqueserver/scripts/smartnade.py
piqueserver/scripts/ratio.py
piqueserver/scripts/votemap.py
piqueserver/scripts/dirtnade.py
piqueserver/scripts/spadenadefix.py
piqueserver/scripts/spawn_protect.py
piqueserver/scripts/minefield.py
piqueserver/scripts/rampage.py
piqueserver/scripts/protect.py
piqueserver/scripts/demolitionman.py
piqueserver/scripts/nospadingwalls.py
piqueserver/scripts/blockinfo.py
piqueserver/scripts/babel_script.py
piqueserver/scripts/spectatorcontrol.py
piqueserver/scripts/mapmakingtools.py
piqueserver/scripts/match.py
piqueserver/scripts/runningman.py
