Metadata-Version: 2.1
Name: piqueserver
Version: 1.3.0
Summary: Open-Source server implementation for Ace of Spades
Author: pyspades, PySnip and piqueserver contributors
Author-email: "Mathias Kærlev (matpow2)" <matpow2@gmail.com>, Nate Shoffner <nate.shoffner@gmail.com>, NotAFile <notafile@gmail.com>
Maintainer-email: NotAFile <notafile@gmail.com>
Project-URL: Homepage, https://piqueserver.org
Project-URL: Documentation, https://docs.piqueserver.org/en/latest/
Project-URL: Repository, https://github.com/piqueserver/piqueserver
Project-URL: Issues, https://github.com/piqueserver/issues
Project-URL: Changelog, https://github.com/piqueserver/piqueserver/releases
Keywords: ace of spades,aos,server,pyspades,pysnip,piqueserver
Classifier: Intended Audience :: System Administrators
Classifier: Development Status :: 5 - Production/Stable
Classifier: Operating System :: MacOS :: MacOS X
Classifier: Operating System :: Unix
Classifier: Operating System :: Microsoft :: Windows
Classifier: Environment :: Console
Classifier: License :: OSI Approved :: GNU General Public License v3 (GPLv3)
Classifier: Programming Language :: Python
Classifier: Programming Language :: Cython
Classifier: Programming Language :: Python :: 3
Classifier: Framework :: Twisted
Classifier: Topic :: Games/Entertainment
Classifier: Topic :: Games/Entertainment :: First Person Shooters
Requires-Python: <3.13,>=3.10
License-File: LICENSE
Requires-Dist: Jinja2<4,>=3.0.0
Requires-Dist: pyenet
Requires-Dist: toml
Requires-Dist: Pillow<11,>=5.1.0
Requires-Dist: aiohttp<3.8.0,>=3.3.0
Requires-Dist: packaging>=19.0
Requires-Dist: Twisted
Requires-Dist: pypiwin32; platform_system == "Windows"
Provides-Extra: dev
Requires-Dist: flake8; extra == "dev"
Requires-Dist: coveralls; extra == "dev"
Requires-Dist: pytest; extra == "dev"
Requires-Dist: pytest-cov; extra == "dev"
Requires-Dist: pytest-asyncio; extra == "dev"
Requires-Dist: Sphinx; extra == "dev"
Requires-Dist: tox; extra == "dev"
Requires-Dist: sphinx-rtd-theme; extra == "dev"
Requires-Dist: Twisted[conch,tls]; extra == "dev"
Provides-Extra: from
Requires-Dist: geoip2<5.0,>=2.9; extra == "from"
Provides-Extra: ssh
Requires-Dist: Twisted[conch,tls]; extra == "ssh"
